uqtestfuns/__init__.py
uqtestfuns/global_settings.py
uqtestfuns/helpers.py
uqtestfuns/py.typed
uqtestfuns/utils.py
uqtestfuns/core/__init__.py
uqtestfuns/core/custom_typing.py
uqtestfuns/core/parameters.py
uqtestfuns/core/uqtestfun.py
uqtestfuns/core/uqtestfun_abc.py
uqtestfuns/core/utils.py
uqtestfuns/core/prob_input/__init__.py
uqtestfuns/core/prob_input/marginal.py
uqtestfuns/core/prob_input/probabilistic_input.py
uqtestfuns/core/prob_input/utils.py
uqtestfuns/core/prob_input/univariate_distributions/__init__.py
uqtestfuns/core/prob_input/univariate_distributions/beta.py
uqtestfuns/core/prob_input/univariate_distributions/exponential.py
uqtestfuns/core/prob_input/univariate_distributions/gumbel.py
uqtestfuns/core/prob_input/univariate_distributions/logitnormal.py
uqtestfuns/core/prob_input/univariate_distributions/lognormal.py
uqtestfuns/core/prob_input/univariate_distributions/normal.py
uqtestfuns/core/prob_input/univariate_distributions/triangular.py
uqtestfuns/core/prob_input/univariate_distributions/trunc_gumbel.py
uqtestfuns/core/prob_input/univariate_distributions/trunc_normal.py
uqtestfuns/core/prob_input/univariate_distributions/uniform.py
uqtestfuns/core/prob_input/univariate_distributions/utils.py
uqtestfuns/meta/__init__.py
uqtestfuns/meta/basis_functions.py
uqtestfuns/meta/metaspec.py
uqtestfuns/meta/uqmetatestfun.py
uqtestfuns/test_functions/__init__.py
uqtestfuns/test_functions/ackley.py
uqtestfuns/test_functions/alemazkoor.py
uqtestfuns/test_functions/borehole.py
uqtestfuns/test_functions/bratley1992.py
uqtestfuns/test_functions/cantilever_beam_2d.py
uqtestfuns/test_functions/cheng2010.py
uqtestfuns/test_functions/circular_pipe_crack.py
uqtestfuns/test_functions/coffee_cup.py
uqtestfuns/test_functions/convex_fail_domain.py
uqtestfuns/test_functions/currin_sine.py
uqtestfuns/test_functions/damped_cosine.py
uqtestfuns/test_functions/damped_oscillator.py
uqtestfuns/test_functions/dette.py
uqtestfuns/test_functions/flood.py
uqtestfuns-0.6.0.dist-info/LICENSE
uqtestfuns-0.6.0.dist-info/METADATA
uqtestfuns-0.6.0.dist-info/WHEEL
uqtestfuns-0.6.0.dist-info/top_level.txt
uqtestfuns-0.6.0.dist-info/RECORD
