Metadata-Version: 2.2
Name: uqtestfuns
Version: 0.6.0
Summary: A Python3 library of test functions from the uncertainty quantification community with a common interface for benchmarking purpose.
Home-page: https://github.com/damar-wicaksono/uqtestfuns
Author: Damar Wicaksono
Author-email: damar.wicaksono@outlook.com
License: MIT
Platform: ANY
Classifier: License :: OSI Approved :: MIT License
Classifier: Programming Language :: Python :: 3
Classifier: Programming Language :: Python :: 3 :: Only
Classifier: Programming Language :: Python :: 3.7
Classifier: Programming Language :: Python :: 3.8
Classifier: Programming Language :: Python :: 3.9
Classifier: Programming Language :: Python :: 3.10
Classifier: Programming Language :: Python :: 3.11
Classifier: Topic :: Scientific/Engineering
Classifier: Topic :: Scientific/Engineering :: Mathematics
Classifier: Topic :: Software Development :: Libraries :: Python Modules
Classifier: Intended Audience :: Science/Research
Requires-Python: >=3.7
License-File: LICENSE
Requires-Dist: numpy>=1.13.3
Requires-Dist: scipy>=1.7.3
Requires-Dist: tabulate>=0.8.10
Requires-Dist: importlib-metadata>=1.0; python_version < "3.8"
Requires-Dist: typing_extensions; python_version > "3.7"
Provides-Extra: dev
Requires-Dist: pytest>=4.6; extra == "dev"
Requires-Dist: pytest-cov>=2.12.0; extra == "dev"
Requires-Dist: pytest-randomly; extra == "dev"
Requires-Dist: black; extra == "dev"
Requires-Dist: flake8; extra == "dev"
Requires-Dist: flake8-bugbear; extra == "dev"
Requires-Dist: mypy; extra == "dev"
Requires-Dist: types-tabulate; extra == "dev"
Requires-Dist: types-setuptools; extra == "dev"
Provides-Extra: docs
Requires-Dist: jupyter-book; extra == "docs"
Requires-Dist: sphinx; extra == "docs"
Requires-Dist: matplotlib>=3.7.0; extra == "docs"
Requires-Dist: sphinx-proof; extra == "docs"
Provides-Extra: all
Requires-Dist: uqtestfuns[dev]; extra == "all"
Requires-Dist: uqtestfuns[docs]; extra == "all"
